{"readme.md":"759b0cfc","components_button_glow-button_index.md":"82e17a6d","components_button-group_multi-button_index.md":"8fb70b1c","components_button_gfg-button_index.md":"fb33b05d","components_noble_collapse_index.md":"06e9a57c","components_noble_overlay_index.md":"15523f2a","components_noble_drawer_index.md":"9bc01313","index.md":"dbef411d","guide_introduction_index.md":"b583b19d","guide_quick-start_index.md":"1c928685","components_noble_button_index.md":"80037428","components_noble_card_index.md":"ff396b8b","components_noble_swiper_index.md":"c2111312"}
